{
  "id": "https://openalex.org/S4210214087",
  "issn_l": "0267-6192",
  "issn": [
    "0267-6192"
  ],
  "display_name": "Computer Systems Science and Engineering",
  "host_organization": null,
  "host_organization_name": null,
  "host_organization_lineage": [],
  "works_count": 1497,
  "oa_works_count": 1497,
  "cited_by_count": 12637,
  "summary_stats": {
    "2yr_mean_citedness": 2.6574074074074074,
    "h_index": 39,
    "i10_index": 378
  },
  "is_oa": true,
  "is_in_doaj": false,
  "is_in_doaj_since_year": null,
  "is_high_oa_rate": true,
  "is_high_oa_rate_since_year": null,
  "is_in_scielo": false,
  "is_ojs": true,
  "is_core": true,
  "oa_flip_year": null,
  "first_publication_year": 2018,
  "last_publication_year": 2025,
  "ids": {
    "openalex": "https://openalex.org/S4210214087",
    "issn_l": "0267-6192",
    "issn": [
      "0267-6192"
    ],
    "mag": "4210214087",
    "wikidata": "http://www.wikidata.org/entity/Q15764788"
  },
  "homepage_url": null,
  "apc_prices": [],
  "apc_usd": null,
  "country_code": "GB",
  "societies": [],
  "alternate_titles": [
    "International journal of computer systems science and engineering"
  ],
  "type": "journal",
  "topics": [
    {
      "id": "https://openalex.org/T10273",
      "display_name": "IoT and Edge/Fog Computing",
      "count": 135,
      "subfield": {
        "id": "https://openalex.org/subfields/1705",
        "display_name": "Computer Networks and Communications"
      },
      "field": {
        "id": "https://openalex.org/fields/17",
        "display_name": "Computer Science"
      },
      "domain": {
        "id": "https://openalex.org/domains/3",
        "display_name": "Physical Sciences"
      }
    },
    {
      "id": "https://openalex.org/T10400",
      "display_name": "Network Security and Intrusion Detection",
      "count": 113,
      "subfield": {
        "id": "https://openalex.org/subfields/1705",
        "display_name": "Computer Networks and Communications"
      },
      "field": {
        "id": "https://openalex.org/fields/17",
        "display_name": "Computer Science"
      },
      "domain": {
        "id": "https://openalex.org/domains/3",
        "display_name": "Physical Sciences"
      }
    },
    {
      "id": "https://openalex.org/T10270",
      "display_name": "Blockchain Technology Applications and Security",
      "count": 76,
      "subfield": {
        "id": "https://openalex.org/subfields/1710",
        "display_name": "Information Systems"
      },
      "field": {
        "id": "https://openalex.org/fields/17",
        "display_name": "Computer Science"
      },
      "domain": {
        "id": "https://openalex.org/domains/3",
        "display_name": "Physical Sciences"
      }
    },
    {
      "id": "https://openalex.org/T11241",
      "display_name": "Advanced Malware Detection Techniques",
      "count": 73,
      "subfield": {
        "id": "https://openalex.org/subfields/1711",
        "display_name": "Signal Processing"
      },
      "field": {
        "id": "https://openalex.org/fields/17",
        "display_name": "Computer Science"
      },
      "domain": {
        "id": "https://openalex.org/domains/3",
        "display_name": "Physical Sciences"
      }
    },
    {
      "id": "https://openalex.org/T10080",
      "display_name": "Energy Efficient Wireless Sensor Networks",
      "count": 67,
      "subfield": {
        "id": "https://openalex.org/subfields/1705",
        "display_name": "Computer Networks and Communications"
      },
      "field": {
        "id": "https://openalex.org/fields/17",
        "display_name": "Computer Science"
      },
      "domain": {
        "id": "https://openalex.org/domains/3",
        "display_name": "Physical Sciences"
      }
    },
    {
      "id": "https://openalex.org/T11512",
      "display_name": "Anomaly Detection Techniques and Applications",
      "count": 67,
      "subfield": {
        "id": "https://openalex.org/subfields/1702",
        "display_name": "Artificial Intelligence"
      },
      "field": {
        "id": "https://openalex.org/fields/17",
        "display_name": "Computer Science"
      },
      "domain": {
        "id": "https://openalex.org/domains/3",
        "display_name": "Physical Sciences"
      }
    },
    {
      "id": "https://openalex.org/T10101",
      "display_name": "Cloud Computing and Resource Management",
      "count": 59,
      "subfield": {
        "id": "https://openalex.org/subfields/1710",
        "display_name": "Information Systems"
      },
      "field": {
        "id": "https://openalex.org/fields/17",
        "display_name": "Computer Science"
      },
      "domain": {
        "id": "https://openalex.org/domains/3",
        "display_name": "Physical Sciences"
      }
    },
    {
      "id": "https://openalex.org/T10862",
      "display_name": "AI in cancer detection",
      "count": 58,
      "subfield": {
        "id": "https://openalex.org/subfields/1702",
        "display_name": "Artificial Intelligence"
      },
      "field": {
        "id": "https://openalex.org/fields/17",
        "display_name": "Computer Science"
      },
      "domain": {
        "id": "https://openalex.org/domains/3",
        "display_name": "Physical Sciences"
      }
    },
    {
      "id": "https://openalex.org/T11775",
      "display_name": "COVID-19 diagnosis using AI",
      "count": 55,
      "subfield": {
        "id": "https://openalex.org/subfields/2741",
        "display_name": "Radiology, Nuclear Medicine and Imaging"
      },
      "field": {
        "id": "https://openalex.org/fields/27",
        "display_name": "Medicine"
      },
      "domain": {
        "id": "https://openalex.org/domains/4",
        "display_name": "Health Sciences"
      }
    },
    {
      "id": "https://openalex.org/T10664",
      "display_name": "Sentiment Analysis and Opinion Mining",
      "count": 51,
      "subfield": {
        "id": "https://openalex.org/subfields/1702",
        "display_name": "Artificial Intelligence"
      },
      "field": {
        "id": "https://openalex.org/fields/17",
        "display_name": "Computer Science"
      },
      "domain": {
        "id": "https://openalex.org/domains/3",
        "display_name": "Physical Sciences"
      }
    },
    {
      "id": "https://openalex.org/T10388",
      "display_name": "Advanced Steganography and Watermarking Techniques",
      "count": 47,
      "subfield": {
        "id": "https://openalex.org/subfields/1707",
        "display_name": "Computer Vision and Pattern Recognition"
      },
      "field": {
        "id": "https://openalex.org/fields/17",
        "display_name": "Computer Science"
      },
      "domain": {
        "id": "https://openalex.org/domains/3",
        "display_name": "Physical Sciences"
      }
    },
    {
      "id": "https://openalex.org/T12702",
      "display_name": "Brain Tumor Detection and Classification",
      "count": 45,
      "subfield": {
        "id": "https://openalex.org/subfields/2808",
        "display_name": "Neurology"
      },
      "field": {
        "id": "https://openalex.org/fields/28",
        "display_name": "Neuroscience"
      },
      "domain": {
        "id": "https://openalex.org/domains/1",
        "display_name": "Life Sciences"
      }
    },
    {
      "id": "https://openalex.org/T10331",
      "display_name": "Video Surveillance and Tracking Methods",
      "count": 41,
      "subfield": {
        "id": "https://openalex.org/subfields/1707",
        "display_name": "Computer Vision and Pattern Recognition"
      },
      "field": {
        "id": "https://openalex.org/fields/17",
        "display_name": "Computer Science"
      },
      "domain": {
        "id": "https://openalex.org/domains/3",
        "display_name": "Physical Sciences"
      }
    },
    {
      "id": "https://openalex.org/T11614",
      "display_name": "Cloud Data Security Solutions",
      "count": 39,
      "subfield": {
        "id": "https://openalex.org/subfields/1710",
        "display_name": "Information Systems"
      },
      "field": {
        "id": "https://openalex.org/fields/17",
        "display_name": "Computer Science"
      },
      "domain": {
        "id": "https://openalex.org/domains/3",
        "display_name": "Physical Sciences"
      }
    },
    {
      "id": "https://openalex.org/T11598",
      "display_name": "Internet Traffic Analysis and Secure E-voting",
      "count": 38,
      "subfield": {
        "id": "https://openalex.org/subfields/1702",
        "display_name": "Artificial Intelligence"
      },
      "field": {
        "id": "https://openalex.org/fields/17",
        "display_name": "Computer Science"
      },
      "domain": {
        "id": "https://openalex.org/domains/3",
        "display_name": "Physical Sciences"
      }
    },
    {
      "id": "https://openalex.org/T10036",
      "display_name": "Advanced Neural Network Applications",
      "count": 37,
      "subfield": {
        "id": "https://openalex.org/subfields/1707",
        "display_name": "Computer Vision and Pattern Recognition"
      },
      "field": {
        "id": "https://openalex.org/fields/17",
        "display_name": "Computer Science"
      },
      "domain": {
        "id": "https://openalex.org/domains/3",
        "display_name": "Physical Sciences"
      }
    },
    {
      "id": "https://openalex.org/T10616",
      "display_name": "Smart Agriculture and AI",
      "count": 37,
      "subfield": {
        "id": "https://openalex.org/subfields/1110",
        "display_name": "Plant Science"
      },
      "field": {
        "id": "https://openalex.org/fields/11",
        "display_name": "Agricultural and Biological Sciences"
      },
      "domain": {
        "id": "https://openalex.org/domains/1",
        "display_name": "Life Sciences"
      }
    },
    {
      "id": "https://openalex.org/T11396",
      "display_name": "Artificial Intelligence in Healthcare",
      "count": 37,
      "subfield": {
        "id": "https://openalex.org/subfields/3605",
        "display_name": "Health Information Management"
      },
      "field": {
        "id": "https://openalex.org/fields/36",
        "display_name": "Health Professions"
      },
      "domain": {
        "id": "https://openalex.org/domains/4",
        "display_name": "Health Sciences"
      }
    },
    {
      "id": "https://openalex.org/T11017",
      "display_name": "Chaos-based Image/Signal Encryption",
      "count": 34,
      "subfield": {
        "id": "https://openalex.org/subfields/1707",
        "display_name": "Computer Vision and Pattern Recognition"
      },
      "field": {
        "id": "https://openalex.org/fields/17",
        "display_name": "Computer Science"
      },
      "domain": {
        "id": "https://openalex.org/domains/3",
        "display_name": "Physical Sciences"
      }
    },
    {
      "id": "https://openalex.org/T12357",
      "display_name": "Digital Media Forensic Detection",
      "count": 34,
      "subfield": {
        "id": "https://openalex.org/subfields/1707",
        "display_name": "Computer Vision and Pattern Recognition"
      },
      "field": {
        "id": "https://openalex.org/fields/17",
        "display_name": "Computer Science"
      },
      "domain": {
        "id": "https://openalex.org/domains/3",
        "display_name": "Physical Sciences"
      }
    },
    {
      "id": "https://openalex.org/T10237",
      "display_name": "Cryptography and Data Security",
      "count": 31,
      "subfield": {
        "id": "https://openalex.org/subfields/1702",
        "display_name": "Artificial Intelligence"
      },
      "field": {
        "id": "https://openalex.org/fields/17",
        "display_name": "Computer Science"
      },
      "domain": {
        "id": "https://openalex.org/domains/3",
        "display_name": "Physical Sciences"
      }
    },
    {
      "id": "https://openalex.org/T10627",
      "display_name": "Advanced Image and Video Retrieval Techniques",
      "count": 31,
      "subfield": {
        "id": "https://openalex.org/subfields/1707",
        "display_name": "Computer Vision and Pattern Recognition"
      },
      "field": {
        "id": "https://openalex.org/fields/17",
        "display_name": "Computer Science"
      },
      "domain": {
        "id": "https://openalex.org/domains/3",
        "display_name": "Physical Sciences"
      }
    },
    {
      "id": "https://openalex.org/T11392",
      "display_name": "Energy Harvesting in Wireless Networks",
      "count": 30,
      "subfield": {
        "id": "https://openalex.org/subfields/2208",
        "display_name": "Electrical and Electronic Engineering"
      },
      "field": {
        "id": "https://openalex.org/fields/22",
        "display_name": "Engineering"
      },
      "domain": {
        "id": "https://openalex.org/domains/3",
        "display_name": "Physical Sciences"
      }
    },
    {
      "id": "https://openalex.org/T11550",
      "display_name": "Text and Document Classification Technologies",
      "count": 30,
      "subfield": {
        "id": "https://openalex.org/subfields/1702",
        "display_name": "Artificial Intelligence"
      },
      "field": {
        "id": "https://openalex.org/fields/17",
        "display_name": "Computer Science"
      },
      "domain": {
        "id": "https://openalex.org/domains/3",
        "display_name": "Physical Sciences"
      }
    },
    {
      "id": "https://openalex.org/T11644",
      "display_name": "Spam and Phishing Detection",
      "count": 30,
      "subfield": {
        "id": "https://openalex.org/subfields/1710",
        "display_name": "Information Systems"
      },
      "field": {
        "id": "https://openalex.org/fields/17",
        "display_name": "Computer Science"
      },
      "domain": {
        "id": "https://openalex.org/domains/3",
        "display_name": "Physical Sciences"
      }
    }
  ],
  "topic_share": [
    {
      "id": "https://openalex.org/T13693",
      "display_name": "Smart Systems and Machine Learning",
      "value": 0.0009266,
      "subfield": {
        "id": "https://openalex.org/subfields/1705",
        "display_name": "Computer Networks and Communications"
      },
      "field": {
        "id": "https://openalex.org/fields/17",
        "display_name": "Computer Science"
      },
      "domain": {
        "id": "https://openalex.org/domains/3",
        "display_name": "Physical Sciences"
      }
    },
    {
      "id": "https://openalex.org/T10273",
      "display_name": "IoT and Edge/Fog Computing",
      "value": 0.0007717,
      "subfield": {
        "id": "https://openalex.org/subfields/1705",
        "display_name": "Computer Networks and Communications"
      },
      "field": {
        "id": "https://openalex.org/fields/17",
        "display_name": "Computer Science"
      },
      "domain": {
        "id": "https://openalex.org/domains/3",
        "display_name": "Physical Sciences"
      }
    },
    {
      "id": "https://openalex.org/T11614",
      "display_name": "Cloud Data Security Solutions",
      "value": 0.0005848,
      "subfield": {
        "id": "https://openalex.org/subfields/1710",
        "display_name": "Information Systems"
      },
      "field": {
        "id": "https://openalex.org/fields/17",
        "display_name": "Computer Science"
      },
      "domain": {
        "id": "https://openalex.org/domains/3",
        "display_name": "Physical Sciences"
      }
    },
    {
      "id": "https://openalex.org/T10388",
      "display_name": "Advanced Steganography and Watermarking Techniques",
      "value": 0.000584,
      "subfield": {
        "id": "https://openalex.org/subfields/1707",
        "display_name": "Computer Vision and Pattern Recognition"
      },
      "field": {
        "id": "https://openalex.org/fields/17",
        "display_name": "Computer Science"
      },
      "domain": {
        "id": "https://openalex.org/domains/3",
        "display_name": "Physical Sciences"
      }
    },
    {
      "id": "https://openalex.org/T10664",
      "display_name": "Sentiment Analysis and Opinion Mining",
      "value": 0.000543,
      "subfield": {
        "id": "https://openalex.org/subfields/1702",
        "display_name": "Artificial Intelligence"
      },
      "field": {
        "id": "https://openalex.org/fields/17",
        "display_name": "Computer Science"
      },
      "domain": {
        "id": "https://openalex.org/domains/3",
        "display_name": "Physical Sciences"
      }
    },
    {
      "id": "https://openalex.org/T10400",
      "display_name": "Network Security and Intrusion Detection",
      "value": 0.0005428,
      "subfield": {
        "id": "https://openalex.org/subfields/1705",
        "display_name": "Computer Networks and Communications"
      },
      "field": {
        "id": "https://openalex.org/fields/17",
        "display_name": "Computer Science"
      },
      "domain": {
        "id": "https://openalex.org/domains/3",
        "display_name": "Physical Sciences"
      }
    },
    {
      "id": "https://openalex.org/T12702",
      "display_name": "Brain Tumor Detection and Classification",
      "value": 0.000527,
      "subfield": {
        "id": "https://openalex.org/subfields/2808",
        "display_name": "Neurology"
      },
      "field": {
        "id": "https://openalex.org/fields/28",
        "display_name": "Neuroscience"
      },
      "domain": {
        "id": "https://openalex.org/domains/1",
        "display_name": "Life Sciences"
      }
    },
    {
      "id": "https://openalex.org/T13345",
      "display_name": "Advanced Technologies and Applied Computing",
      "value": 0.0005027,
      "subfield": {
        "id": "https://openalex.org/subfields/1705",
        "display_name": "Computer Networks and Communications"
      },
      "field": {
        "id": "https://openalex.org/fields/17",
        "display_name": "Computer Science"
      },
      "domain": {
        "id": "https://openalex.org/domains/3",
        "display_name": "Physical Sciences"
      }
    },
    {
      "id": "https://openalex.org/T10080",
      "display_name": "Energy Efficient Wireless Sensor Networks",
      "value": 0.0004956,
      "subfield": {
        "id": "https://openalex.org/subfields/1705",
        "display_name": "Computer Networks and Communications"
      },
      "field": {
        "id": "https://openalex.org/fields/17",
        "display_name": "Computer Science"
      },
      "domain": {
        "id": "https://openalex.org/domains/3",
        "display_name": "Physical Sciences"
      }
    },
    {
      "id": "https://openalex.org/T11775",
      "display_name": "COVID-19 diagnosis using AI",
      "value": 0.0004851,
      "subfield": {
        "id": "https://openalex.org/subfields/2741",
        "display_name": "Radiology, Nuclear Medicine and Imaging"
      },
      "field": {
        "id": "https://openalex.org/fields/27",
        "display_name": "Medicine"
      },
      "domain": {
        "id": "https://openalex.org/domains/4",
        "display_name": "Health Sciences"
      }
    },
    {
      "id": "https://openalex.org/T12357",
      "display_name": "Digital Media Forensic Detection",
      "value": 0.0004786,
      "subfield": {
        "id": "https://openalex.org/subfields/1707",
        "display_name": "Computer Vision and Pattern Recognition"
      },
      "field": {
        "id": "https://openalex.org/fields/17",
        "display_name": "Computer Science"
      },
      "domain": {
        "id": "https://openalex.org/domains/3",
        "display_name": "Physical Sciences"
      }
    },
    {
      "id": "https://openalex.org/T11241",
      "display_name": "Advanced Malware Detection Techniques",
      "value": 0.0004754,
      "subfield": {
        "id": "https://openalex.org/subfields/1711",
        "display_name": "Signal Processing"
      },
      "field": {
        "id": "https://openalex.org/fields/17",
        "display_name": "Computer Science"
      },
      "domain": {
        "id": "https://openalex.org/domains/3",
        "display_name": "Physical Sciences"
      }
    },
    {
      "id": "https://openalex.org/T11498",
      "display_name": "Security in Wireless Sensor Networks",
      "value": 0.0004466,
      "subfield": {
        "id": "https://openalex.org/subfields/1705",
        "display_name": "Computer Networks and Communications"
      },
      "field": {
        "id": "https://openalex.org/fields/17",
        "display_name": "Computer Science"
      },
      "domain": {
        "id": "https://openalex.org/domains/3",
        "display_name": "Physical Sciences"
      }
    },
    {
      "id": "https://openalex.org/T10270",
      "display_name": "Blockchain Technology Applications and Security",
      "value": 0.0004347,
      "subfield": {
        "id": "https://openalex.org/subfields/1710",
        "display_name": "Information Systems"
      },
      "field": {
        "id": "https://openalex.org/fields/17",
        "display_name": "Computer Science"
      },
      "domain": {
        "id": "https://openalex.org/domains/3",
        "display_name": "Physical Sciences"
      }
    },
    {
      "id": "https://openalex.org/T10828",
      "display_name": "Biometric Identification and Security",
      "value": 0.000431,
      "subfield": {
        "id": "https://openalex.org/subfields/1711",
        "display_name": "Signal Processing"
      },
      "field": {
        "id": "https://openalex.org/fields/17",
        "display_name": "Computer Science"
      },
      "domain": {
        "id": "https://openalex.org/domains/3",
        "display_name": "Physical Sciences"
      }
    },
    {
      "id": "https://openalex.org/T12079",
      "display_name": "IoT Networks and Protocols",
      "value": 0.0004256,
      "subfield": {
        "id": "https://openalex.org/subfields/2208",
        "display_name": "Electrical and Electronic Engineering"
      },
      "field": {
        "id": "https://openalex.org/fields/22",
        "display_name": "Engineering"
      },
      "domain": {
        "id": "https://openalex.org/domains/3",
        "display_name": "Physical Sciences"
      }
    },
    {
      "id": "https://openalex.org/T11598",
      "display_name": "Internet Traffic Analysis and Secure E-voting",
      "value": 0.00042,
      "subfield": {
        "id": "https://openalex.org/subfields/1702",
        "display_name": "Artificial Intelligence"
      },
      "field": {
        "id": "https://openalex.org/fields/17",
        "display_name": "Computer Science"
      },
      "domain": {
        "id": "https://openalex.org/domains/3",
        "display_name": "Physical Sciences"
      }
    },
    {
      "id": "https://openalex.org/T11800",
      "display_name": "User Authentication and Security Systems",
      "value": 0.0004035,
      "subfield": {
        "id": "https://openalex.org/subfields/1710",
        "display_name": "Information Systems"
      },
      "field": {
        "id": "https://openalex.org/fields/17",
        "display_name": "Computer Science"
      },
      "domain": {
        "id": "https://openalex.org/domains/3",
        "display_name": "Physical Sciences"
      }
    },
    {
      "id": "https://openalex.org/T11512",
      "display_name": "Anomaly Detection Techniques and Applications",
      "value": 0.0003948,
      "subfield": {
        "id": "https://openalex.org/subfields/1702",
        "display_name": "Artificial Intelligence"
      },
      "field": {
        "id": "https://openalex.org/fields/17",
        "display_name": "Computer Science"
      },
      "domain": {
        "id": "https://openalex.org/domains/3",
        "display_name": "Physical Sciences"
      }
    },
    {
      "id": "https://openalex.org/T12676",
      "display_name": "Machine Learning and ELM",
      "value": 0.0003811,
      "subfield": {
        "id": "https://openalex.org/subfields/1702",
        "display_name": "Artificial Intelligence"
      },
      "field": {
        "id": "https://openalex.org/fields/17",
        "display_name": "Computer Science"
      },
      "domain": {
        "id": "https://openalex.org/domains/3",
        "display_name": "Physical Sciences"
      }
    },
    {
      "id": "https://openalex.org/T11550",
      "display_name": "Text and Document Classification Technologies",
      "value": 0.0003754,
      "subfield": {
        "id": "https://openalex.org/subfields/1702",
        "display_name": "Artificial Intelligence"
      },
      "field": {
        "id": "https://openalex.org/fields/17",
        "display_name": "Computer Science"
      },
      "domain": {
        "id": "https://openalex.org/domains/3",
        "display_name": "Physical Sciences"
      }
    },
    {
      "id": "https://openalex.org/T11644",
      "display_name": "Spam and Phishing Detection",
      "value": 0.000368,
      "subfield": {
        "id": "https://openalex.org/subfields/1710",
        "display_name": "Information Systems"
      },
      "field": {
        "id": "https://openalex.org/fields/17",
        "display_name": "Computer Science"
      },
      "domain": {
        "id": "https://openalex.org/domains/3",
        "display_name": "Physical Sciences"
      }
    },
    {
      "id": "https://openalex.org/T10862",
      "display_name": "AI in cancer detection",
      "value": 0.0003636,
      "subfield": {
        "id": "https://openalex.org/subfields/1702",
        "display_name": "Artificial Intelligence"
      },
      "field": {
        "id": "https://openalex.org/fields/17",
        "display_name": "Computer Science"
      },
      "domain": {
        "id": "https://openalex.org/domains/3",
        "display_name": "Physical Sciences"
      }
    },
    {
      "id": "https://openalex.org/T11504",
      "display_name": "Advanced Authentication Protocols Security",
      "value": 0.0003422,
      "subfield": {
        "id": "https://openalex.org/subfields/1705",
        "display_name": "Computer Networks and Communications"
      },
      "field": {
        "id": "https://openalex.org/fields/17",
        "display_name": "Computer Science"
      },
      "domain": {
        "id": "https://openalex.org/domains/3",
        "display_name": "Physical Sciences"
      }
    },
    {
      "id": "https://openalex.org/T10331",
      "display_name": "Video Surveillance and Tracking Methods",
      "value": 0.0003366,
      "subfield": {
        "id": "https://openalex.org/subfields/1707",
        "display_name": "Computer Vision and Pattern Recognition"
      },
      "field": {
        "id": "https://openalex.org/fields/17",
        "display_name": "Computer Science"
      },
      "domain": {
        "id": "https://openalex.org/domains/3",
        "display_name": "Physical Sciences"
      }
    }
  ],
  "counts_by_year": [
    {
      "year": 2025,
      "works_count": 17,
      "oa_works_count": 17,
      "cited_by_count": 6
    },
    {
      "year": 2024,
      "works_count": 91,
      "oa_works_count": 91,
      "cited_by_count": 281
    },
    {
      "year": 2023,
      "works_count": 410,
      "oa_works_count": 410,
      "cited_by_count": 2545
    },
    {
      "year": 2022,
      "works_count": 530,
      "oa_works_count": 530,
      "cited_by_count": 4668
    },
    {
      "year": 2021,
      "works_count": 306,
      "oa_works_count": 306,
      "cited_by_count": 3923
    },
    {
      "year": 2020,
      "works_count": 65,
      "oa_works_count": 65,
      "cited_by_count": 706
    },
    {
      "year": 2019,
      "works_count": 34,
      "oa_works_count": 34,
      "cited_by_count": 386
    },
    {
      "year": 2018,
      "works_count": 43,
      "oa_works_count": 43,
      "cited_by_count": 122
    },
    {
      "year": 1993,
      "works_count": 1,
      "oa_works_count": 1,
      "cited_by_count": 0
    }
  ],
  "works_api_url": "https://api.openalex.org/works?filter=primary_location.source.id:S4210214087",
  "updated_date": "2026-03-02T20:52:56",
  "created_date": "2022-05-05T00:00:00"
}