{
  "id": "https://openalex.org/I8692664",
  "ror": "https://ror.org/02aqsxs83",
  "display_name": "University of Oklahoma",
  "country_code": "US",
  "type": "education",
  "type_id": "https://openalex.org/institution-types/education",
  "lineage": [
    "https://openalex.org/I8692664"
  ],
  "homepage_url": "https://www.ou.edu",
  "image_url": "https://commons.wikimedia.org/w/index.php?title=Special:Redirect/file/Oklahoma%20Sooners%20logo.svg",
  "image_thumbnail_url": "https://commons.wikimedia.org/w/index.php?title=Special:Redirect/file/Oklahoma%20Sooners%20logo.svg&width=300",
  "display_name_acronyms": [
    "UO"
  ],
  "display_name_alternatives": [
    "Universidad de Oklahoma",
    "University of Oklahoma"
  ],
  "repositories": [
    {
      "id": "https://openalex.org/S4306401289",
      "display_name": "SHAREOK (University of Oklahoma)",
      "host_organization": "https://openalex.org/I8692664",
      "host_organization_name": "University of Oklahoma",
      "host_organization_lineage": [
        "https://openalex.org/I8692664"
      ]
    },
    {
      "id": "https://openalex.org/S4306401290",
      "display_name": "SHAREOK (University of Oklahoma)",
      "host_organization": "https://openalex.org/I8692664",
      "host_organization_name": "University of Oklahoma",
      "host_organization_lineage": [
        "https://openalex.org/I8692664"
      ]
    },
    {
      "id": "https://openalex.org/S4306401768",
      "display_name": "American Review of Politics (University of Oklahoma)",
      "host_organization": "https://openalex.org/I8692664",
      "host_organization_name": "University of Oklahoma",
      "host_organization_lineage": [
        "https://openalex.org/I8692664"
      ]
    },
    {
      "id": "https://openalex.org/S4306401769",
      "display_name": "American Review of Politics (University of Oklahoma)",
      "host_organization": "https://openalex.org/I8692664",
      "host_organization_name": "University of Oklahoma",
      "host_organization_lineage": [
        "https://openalex.org/I8692664"
      ]
    },
    {
      "id": "https://openalex.org/S4306402580",
      "display_name": "Journal of Higher Education Athletics & Innovation (University of Oklahoma)",
      "host_organization": "https://openalex.org/I8692664",
      "host_organization_name": "University of Oklahoma",
      "host_organization_lineage": [
        "https://openalex.org/I8692664"
      ]
    },
    {
      "id": "https://openalex.org/S4306402630",
      "display_name": "Interdisciplinary Journal of Signage and Wayfinding (University of Oklahoma)",
      "host_organization": "https://openalex.org/I8692664",
      "host_organization_name": "University of Oklahoma",
      "host_organization_lineage": [
        "https://openalex.org/I8692664"
      ]
    },
    {
      "id": "https://openalex.org/S4377196510",
      "display_name": "University of Oklahoma College of Law - Digital Commons (University of Oklahoma)",
      "host_organization": "https://openalex.org/I8692664",
      "host_organization_name": "University of Oklahoma",
      "host_organization_lineage": [
        "https://openalex.org/I8692664"
      ]
    }
  ],
  "works_count": 86725,
  "cited_by_count": 6126525,
  "summary_stats": {
    "2yr_mean_citedness": 3.0593866708747566,
    "h_index": 647,
    "i10_index": 83920
  },
  "ids": {
    "openalex": "https://openalex.org/I8692664",
    "ror": "https://ror.org/02aqsxs83",
    "grid": "grid.266900.b",
    "wikipedia": "http://en.wikipedia.org/wiki/University_of_Oklahoma",
    "wikidata": "Q640652"
  },
  "geo": {
    "city": "Norman",
    "geonames_city_id": "4543762",
    "region": "Oklahoma",
    "country_code": "US",
    "country": "United States",
    "latitude": 35.22257,
    "longitude": -97.43948
  },
  "international": {},
  "associated_institutions": [
    {
      "id": "https://openalex.org/I2803024077",
      "ror": "https://ror.org/01w8whh21",
      "display_name": "University of Oklahoma Medical Center",
      "country_code": "US",
      "type": "healthcare",
      "relationship": "related"
    },
    {
      "id": "https://openalex.org/I4210099251",
      "ror": "https://ror.org/010md9d18",
      "display_name": "Oklahoma City VA Medical Center",
      "country_code": "US",
      "type": "healthcare",
      "relationship": "related"
    },
    {
      "id": "https://openalex.org/I4210112443",
      "ror": "https://ror.org/020xgge28",
      "display_name": "Oklahoma Space Grant Consortium",
      "country_code": "US",
      "type": "other",
      "relationship": "child"
    },
    {
      "id": "https://openalex.org/I4387156350",
      "ror": "https://ror.org/05066y189",
      "display_name": "South Central Climate Adaptation Science Center",
      "country_code": null,
      "type": "facility",
      "relationship": "child"
    },
    {
      "id": "https://openalex.org/I4392738079",
      "ror": "https://ror.org/04g1a0w27",
      "display_name": "University of Oklahoma - Tulsa",
      "country_code": null,
      "type": "education",
      "relationship": "child"
    },
    {
      "id": "https://openalex.org/I4405262545",
      "ror": "https://ror.org/03y3v2a89",
      "display_name": "Oklahoma Geological Survey",
      "country_code": "US",
      "type": "government",
      "relationship": "child"
    },
    {
      "id": "https://openalex.org/I49332381",
      "ror": "https://ror.org/0457zbj98",
      "display_name": "University of Oklahoma Health Sciences Center",
      "country_code": "US",
      "type": "healthcare",
      "relationship": "related"
    }
  ],
  "counts_by_year": [
    {
      "year": 2109,
      "works_count": 1,
      "oa_works_count": 1,
      "cited_by_count": 0
    },
    {
      "year": 2026,
      "works_count": 599,
      "oa_works_count": 368,
      "cited_by_count": 98
    },
    {
      "year": 2025,
      "works_count": 3743,
      "oa_works_count": 2145,
      "cited_by_count": 4378
    },
    {
      "year": 2024,
      "works_count": 4345,
      "oa_works_count": 2776,
      "cited_by_count": 20045
    },
    {
      "year": 2023,
      "works_count": 4245,
      "oa_works_count": 2826,
      "cited_by_count": 32624
    },
    {
      "year": 2022,
      "works_count": 3570,
      "oa_works_count": 2117,
      "cited_by_count": 50018
    },
    {
      "year": 2021,
      "works_count": 3475,
      "oa_works_count": 1996,
      "cited_by_count": 62084
    },
    {
      "year": 2020,
      "works_count": 4024,
      "oa_works_count": 2337,
      "cited_by_count": 83683
    },
    {
      "year": 2019,
      "works_count": 3468,
      "oa_works_count": 1632,
      "cited_by_count": 88626
    },
    {
      "year": 2018,
      "works_count": 3181,
      "oa_works_count": 1324,
      "cited_by_count": 96439
    },
    {
      "year": 2017,
      "works_count": 3167,
      "oa_works_count": 1162,
      "cited_by_count": 91645
    },
    {
      "year": 2016,
      "works_count": 3226,
      "oa_works_count": 1405,
      "cited_by_count": 94030
    },
    {
      "year": 2015,
      "works_count": 2991,
      "oa_works_count": 1174,
      "cited_by_count": 98899
    },
    {
      "year": 2014,
      "works_count": 2902,
      "oa_works_count": 992,
      "cited_by_count": 89753
    },
    {
      "year": 2013,
      "works_count": 2687,
      "oa_works_count": 1028,
      "cited_by_count": 90076
    },
    {
      "year": 2012,
      "works_count": 2511,
      "oa_works_count": 1011,
      "cited_by_count": 125332
    },
    {
      "year": 2011,
      "works_count": 2461,
      "oa_works_count": 785,
      "cited_by_count": 91097
    },
    {
      "year": 2010,
      "works_count": 2209,
      "oa_works_count": 617,
      "cited_by_count": 86430
    }
  ],
  "roles": [
    {
      "role": "funder",
      "id": "https://openalex.org/F4320310179",
      "works_count": 8842
    },
    {
      "role": "institution",
      "id": "https://openalex.org/I8692664",
      "works_count": 86725
    },
    {
      "role": "publisher",
      "id": "https://openalex.org/P4310316126",
      "works_count": 80889
    }
  ],
  "topics": [
    {
      "id": "https://openalex.org/T10466",
      "display_name": "Meteorological Phenomena and Simulations",
      "count": 3824,
      "score": 1.0,
      "subfield": {
        "id": "https://openalex.org/subfields/1902",
        "display_name": "Atmospheric Science"
      },
      "field": {
        "id": "https://openalex.org/fields/19",
        "display_name": "Earth and Planetary Sciences"
      },
      "domain": {
        "id": "https://openalex.org/domains/3",
        "display_name": "Physical Sciences"
      }
    },
    {
      "id": "https://openalex.org/T10048",
      "display_name": "Particle physics theoretical and experimental studies",
      "count": 3385,
      "score": 1.0,
      "subfield": {
        "id": "https://openalex.org/subfields/3106",
        "display_name": "Nuclear and High Energy Physics"
      },
      "field": {
        "id": "https://openalex.org/fields/31",
        "display_name": "Physics and Astronomy"
      },
      "domain": {
        "id": "https://openalex.org/domains/3",
        "display_name": "Physical Sciences"
      }
    },
    {
      "id": "https://openalex.org/T10635",
      "display_name": "Hydraulic Fracturing and Reservoir Analysis",
      "count": 2353,
      "score": 1.0,
      "subfield": {
        "id": "https://openalex.org/subfields/2210",
        "display_name": "Mechanical Engineering"
      },
      "field": {
        "id": "https://openalex.org/fields/22",
        "display_name": "Engineering"
      },
      "domain": {
        "id": "https://openalex.org/domains/3",
        "display_name": "Physical Sciences"
      }
    },
    {
      "id": "https://openalex.org/T10527",
      "display_name": "High-Energy Particle Collisions Research",
      "count": 2331,
      "score": 1.0,
      "subfield": {
        "id": "https://openalex.org/subfields/3106",
        "display_name": "Nuclear and High Energy Physics"
      },
      "field": {
        "id": "https://openalex.org/fields/31",
        "display_name": "Physics and Astronomy"
      },
      "domain": {
        "id": "https://openalex.org/domains/3",
        "display_name": "Physical Sciences"
      }
    },
    {
      "id": "https://openalex.org/T10029",
      "display_name": "Climate variability and models",
      "count": 2168,
      "score": 1.0,
      "subfield": {
        "id": "https://openalex.org/subfields/2306",
        "display_name": "Global and Planetary Change"
      },
      "field": {
        "id": "https://openalex.org/fields/23",
        "display_name": "Environmental Science"
      },
      "domain": {
        "id": "https://openalex.org/domains/3",
        "display_name": "Physical Sciences"
      }
    },
    {
      "id": "https://openalex.org/T10892",
      "display_name": "Drilling and Well Engineering",
      "count": 1602,
      "score": 1.0,
      "subfield": {
        "id": "https://openalex.org/subfields/2212",
        "display_name": "Ocean Engineering"
      },
      "field": {
        "id": "https://openalex.org/fields/22",
        "display_name": "Engineering"
      },
      "domain": {
        "id": "https://openalex.org/domains/3",
        "display_name": "Physical Sciences"
      }
    },
    {
      "id": "https://openalex.org/T11234",
      "display_name": "Precipitation Measurement and Analysis",
      "count": 1563,
      "score": 1.0,
      "subfield": {
        "id": "https://openalex.org/subfields/1902",
        "display_name": "Atmospheric Science"
      },
      "field": {
        "id": "https://openalex.org/fields/19",
        "display_name": "Earth and Planetary Sciences"
      },
      "domain": {
        "id": "https://openalex.org/domains/3",
        "display_name": "Physical Sciences"
      }
    },
    {
      "id": "https://openalex.org/T10224",
      "display_name": "Quantum Chromodynamics and Particle Interactions",
      "count": 1511,
      "score": 1.0,
      "subfield": {
        "id": "https://openalex.org/subfields/3106",
        "display_name": "Nuclear and High Energy Physics"
      },
      "field": {
        "id": "https://openalex.org/fields/31",
        "display_name": "Physics and Astronomy"
      },
      "domain": {
        "id": "https://openalex.org/domains/3",
        "display_name": "Physical Sciences"
      }
    },
    {
      "id": "https://openalex.org/T10399",
      "display_name": "Hydrocarbon exploration and reservoir analysis",
      "count": 1197,
      "score": 1.0,
      "subfield": {
        "id": "https://openalex.org/subfields/2211",
        "display_name": "Mechanics of Materials"
      },
      "field": {
        "id": "https://openalex.org/fields/22",
        "display_name": "Engineering"
      },
      "domain": {
        "id": "https://openalex.org/domains/3",
        "display_name": "Physical Sciences"
      }
    },
    {
      "id": "https://openalex.org/T11801",
      "display_name": "Reservoir Engineering and Simulation Methods",
      "count": 1189,
      "score": 1.0,
      "subfield": {
        "id": "https://openalex.org/subfields/2212",
        "display_name": "Ocean Engineering"
      },
      "field": {
        "id": "https://openalex.org/fields/22",
        "display_name": "Engineering"
      },
      "domain": {
        "id": "https://openalex.org/domains/3",
        "display_name": "Physical Sciences"
      }
    },
    {
      "id": "https://openalex.org/T11044",
      "display_name": "Particle Detector Development and Performance",
      "count": 1111,
      "score": 1.0,
      "subfield": {
        "id": "https://openalex.org/subfields/3106",
        "display_name": "Nuclear and High Energy Physics"
      },
      "field": {
        "id": "https://openalex.org/fields/31",
        "display_name": "Physics and Astronomy"
      },
      "domain": {
        "id": "https://openalex.org/domains/3",
        "display_name": "Physical Sciences"
      }
    },
    {
      "id": "https://openalex.org/T10271",
      "display_name": "Seismic Imaging and Inversion Techniques",
      "count": 1089,
      "score": 1.0,
      "subfield": {
        "id": "https://openalex.org/subfields/1908",
        "display_name": "Geophysics"
      },
      "field": {
        "id": "https://openalex.org/fields/19",
        "display_name": "Earth and Planetary Sciences"
      },
      "domain": {
        "id": "https://openalex.org/domains/3",
        "display_name": "Physical Sciences"
      }
    },
    {
      "id": "https://openalex.org/T11483",
      "display_name": "Tropical and Extratropical Cyclones Research",
      "count": 1048,
      "score": 1.0,
      "subfield": {
        "id": "https://openalex.org/subfields/1902",
        "display_name": "Atmospheric Science"
      },
      "field": {
        "id": "https://openalex.org/fields/19",
        "display_name": "Earth and Planetary Sciences"
      },
      "domain": {
        "id": "https://openalex.org/domains/3",
        "display_name": "Physical Sciences"
      }
    },
    {
      "id": "https://openalex.org/T11405",
      "display_name": "Geophysics and Gravity Measurements",
      "count": 973,
      "score": 1.0,
      "subfield": {
        "id": "https://openalex.org/subfields/1910",
        "display_name": "Oceanography"
      },
      "field": {
        "id": "https://openalex.org/fields/19",
        "display_name": "Earth and Planetary Sciences"
      },
      "domain": {
        "id": "https://openalex.org/domains/3",
        "display_name": "Physical Sciences"
      }
    },
    {
      "id": "https://openalex.org/T10995",
      "display_name": "Methane Hydrates and Related Phenomena",
      "count": 971,
      "score": 1.0,
      "subfield": {
        "id": "https://openalex.org/subfields/2304",
        "display_name": "Environmental Chemistry"
      },
      "field": {
        "id": "https://openalex.org/fields/23",
        "display_name": "Environmental Science"
      },
      "domain": {
        "id": "https://openalex.org/domains/3",
        "display_name": "Physical Sciences"
      }
    },
    {
      "id": "https://openalex.org/T10347",
      "display_name": "Atmospheric aerosols and clouds",
      "count": 953,
      "score": 1.0,
      "subfield": {
        "id": "https://openalex.org/subfields/2306",
        "display_name": "Global and Planetary Change"
      },
      "field": {
        "id": "https://openalex.org/fields/23",
        "display_name": "Environmental Science"
      },
      "domain": {
        "id": "https://openalex.org/domains/3",
        "display_name": "Physical Sciences"
      }
    },
    {
      "id": "https://openalex.org/T11588",
      "display_name": "Atmospheric and Environmental Gas Dynamics",
      "count": 934,
      "score": 1.0,
      "subfield": {
        "id": "https://openalex.org/subfields/2306",
        "display_name": "Global and Planetary Change"
      },
      "field": {
        "id": "https://openalex.org/fields/23",
        "display_name": "Environmental Science"
      },
      "domain": {
        "id": "https://openalex.org/domains/3",
        "display_name": "Physical Sciences"
      }
    },
    {
      "id": "https://openalex.org/T10159",
      "display_name": "Ionosphere and magnetosphere dynamics",
      "count": 883,
      "score": 1.0,
      "subfield": {
        "id": "https://openalex.org/subfields/3103",
        "display_name": "Astronomy and Astrophysics"
      },
      "field": {
        "id": "https://openalex.org/fields/31",
        "display_name": "Physics and Astronomy"
      },
      "domain": {
        "id": "https://openalex.org/domains/3",
        "display_name": "Physical Sciences"
      }
    },
    {
      "id": "https://openalex.org/T10039",
      "display_name": "Stellar, planetary, and galactic studies",
      "count": 852,
      "score": 1.0,
      "subfield": {
        "id": "https://openalex.org/subfields/3103",
        "display_name": "Astronomy and Astrophysics"
      },
      "field": {
        "id": "https://openalex.org/fields/31",
        "display_name": "Physics and Astronomy"
      },
      "domain": {
        "id": "https://openalex.org/domains/3",
        "display_name": "Physical Sciences"
      }
    },
    {
      "id": "https://openalex.org/T11791",
      "display_name": "Microbial Community Ecology and Physiology",
      "count": 816,
      "score": 1.0,
      "subfield": {
        "id": "https://openalex.org/subfields/2303",
        "display_name": "Ecology"
      },
      "field": {
        "id": "https://openalex.org/fields/23",
        "display_name": "Environmental Science"
      },
      "domain": {
        "id": "https://openalex.org/domains/3",
        "display_name": "Physical Sciences"
      }
    },
    {
      "id": "https://openalex.org/T10491",
      "display_name": "Enhanced Oil Recovery Techniques",
      "count": 808,
      "score": 1.0,
      "subfield": {
        "id": "https://openalex.org/subfields/2212",
        "display_name": "Ocean Engineering"
      },
      "field": {
        "id": "https://openalex.org/fields/22",
        "display_name": "Engineering"
      },
      "domain": {
        "id": "https://openalex.org/domains/3",
        "display_name": "Physical Sciences"
      }
    },
    {
      "id": "https://openalex.org/T11757",
      "display_name": "Seismic Waves and Analysis",
      "count": 712,
      "score": 1.0,
      "subfield": {
        "id": "https://openalex.org/subfields/1908",
        "display_name": "Geophysics"
      },
      "field": {
        "id": "https://openalex.org/fields/19",
        "display_name": "Earth and Planetary Sciences"
      },
      "domain": {
        "id": "https://openalex.org/domains/3",
        "display_name": "Physical Sciences"
      }
    },
    {
      "id": "https://openalex.org/T10266",
      "display_name": "Plant Water Relations and Carbon Dynamics",
      "count": 691,
      "score": 1.0,
      "subfield": {
        "id": "https://openalex.org/subfields/2306",
        "display_name": "Global and Planetary Change"
      },
      "field": {
        "id": "https://openalex.org/fields/23",
        "display_name": "Environmental Science"
      },
      "domain": {
        "id": "https://openalex.org/domains/3",
        "display_name": "Physical Sciences"
      }
    },
    {
      "id": "https://openalex.org/T11371",
      "display_name": "Wind and Air Flow Studies",
      "count": 687,
      "score": 1.0,
      "subfield": {
        "id": "https://openalex.org/subfields/2305",
        "display_name": "Environmental Engineering"
      },
      "field": {
        "id": "https://openalex.org/fields/23",
        "display_name": "Environmental Science"
      },
      "domain": {
        "id": "https://openalex.org/domains/3",
        "display_name": "Physical Sciences"
      }
    },
    {
      "id": "https://openalex.org/T10487",
      "display_name": "Plant and animal studies",
      "count": 681,
      "score": 1.0,
      "subfield": {
        "id": "https://openalex.org/subfields/1105",
        "display_name": "Ecology, Evolution, Behavior and Systematics"
      },
      "field": {
        "id": "https://openalex.org/fields/11",
        "display_name": "Agricultural and Biological Sciences"
      },
      "domain": {
        "id": "https://openalex.org/domains/1",
        "display_name": "Life Sciences"
      }
    }
  ],
  "topic_share": [
    {
      "id": "https://openalex.org/T10466",
      "display_name": "Meteorological Phenomena and Simulations",
      "value": 0.0162832,
      "subfield": {
        "id": "https://openalex.org/subfields/1902",
        "display_name": "Atmospheric Science"
      },
      "field": {
        "id": "https://openalex.org/fields/19",
        "display_name": "Earth and Planetary Sciences"
      },
      "domain": {
        "id": "https://openalex.org/domains/3",
        "display_name": "Physical Sciences"
      }
    },
    {
      "id": "https://openalex.org/T11234",
      "display_name": "Precipitation Measurement and Analysis",
      "value": 0.0115085,
      "subfield": {
        "id": "https://openalex.org/subfields/1902",
        "display_name": "Atmospheric Science"
      },
      "field": {
        "id": "https://openalex.org/fields/19",
        "display_name": "Earth and Planetary Sciences"
      },
      "domain": {
        "id": "https://openalex.org/domains/3",
        "display_name": "Physical Sciences"
      }
    },
    {
      "id": "https://openalex.org/T10635",
      "display_name": "Hydraulic Fracturing and Reservoir Analysis",
      "value": 0.0113741,
      "subfield": {
        "id": "https://openalex.org/subfields/2210",
        "display_name": "Mechanical Engineering"
      },
      "field": {
        "id": "https://openalex.org/fields/22",
        "display_name": "Engineering"
      },
      "domain": {
        "id": "https://openalex.org/domains/3",
        "display_name": "Physical Sciences"
      }
    },
    {
      "id": "https://openalex.org/T10892",
      "display_name": "Drilling and Well Engineering",
      "value": 0.0092021,
      "subfield": {
        "id": "https://openalex.org/subfields/2212",
        "display_name": "Ocean Engineering"
      },
      "field": {
        "id": "https://openalex.org/fields/22",
        "display_name": "Engineering"
      },
      "domain": {
        "id": "https://openalex.org/domains/3",
        "display_name": "Physical Sciences"
      }
    },
    {
      "id": "https://openalex.org/T13939",
      "display_name": "Archaeology and Natural History",
      "value": 0.00885,
      "subfield": {
        "id": "https://openalex.org/subfields/3314",
        "display_name": "Anthropology"
      },
      "field": {
        "id": "https://openalex.org/fields/33",
        "display_name": "Social Sciences"
      },
      "domain": {
        "id": "https://openalex.org/domains/2",
        "display_name": "Social Sciences"
      }
    },
    {
      "id": "https://openalex.org/T11483",
      "display_name": "Tropical and Extratropical Cyclones Research",
      "value": 0.0088379,
      "subfield": {
        "id": "https://openalex.org/subfields/1902",
        "display_name": "Atmospheric Science"
      },
      "field": {
        "id": "https://openalex.org/fields/19",
        "display_name": "Earth and Planetary Sciences"
      },
      "domain": {
        "id": "https://openalex.org/domains/3",
        "display_name": "Physical Sciences"
      }
    },
    {
      "id": "https://openalex.org/T10029",
      "display_name": "Climate variability and models",
      "value": 0.0079726,
      "subfield": {
        "id": "https://openalex.org/subfields/2306",
        "display_name": "Global and Planetary Change"
      },
      "field": {
        "id": "https://openalex.org/fields/23",
        "display_name": "Environmental Science"
      },
      "domain": {
        "id": "https://openalex.org/domains/3",
        "display_name": "Physical Sciences"
      }
    },
    {
      "id": "https://openalex.org/T10527",
      "display_name": "High-Energy Particle Collisions Research",
      "value": 0.0076357,
      "subfield": {
        "id": "https://openalex.org/subfields/3106",
        "display_name": "Nuclear and High Energy Physics"
      },
      "field": {
        "id": "https://openalex.org/fields/31",
        "display_name": "Physics and Astronomy"
      },
      "domain": {
        "id": "https://openalex.org/domains/3",
        "display_name": "Physical Sciences"
      }
    },
    {
      "id": "https://openalex.org/T10491",
      "display_name": "Enhanced Oil Recovery Techniques",
      "value": 0.0070504,
      "subfield": {
        "id": "https://openalex.org/subfields/2212",
        "display_name": "Ocean Engineering"
      },
      "field": {
        "id": "https://openalex.org/fields/22",
        "display_name": "Engineering"
      },
      "domain": {
        "id": "https://openalex.org/domains/3",
        "display_name": "Physical Sciences"
      }
    },
    {
      "id": "https://openalex.org/T11801",
      "display_name": "Reservoir Engineering and Simulation Methods",
      "value": 0.0068089,
      "subfield": {
        "id": "https://openalex.org/subfields/2212",
        "display_name": "Ocean Engineering"
      },
      "field": {
        "id": "https://openalex.org/fields/22",
        "display_name": "Engineering"
      },
      "domain": {
        "id": "https://openalex.org/domains/3",
        "display_name": "Physical Sciences"
      }
    },
    {
      "id": "https://openalex.org/T11044",
      "display_name": "Particle Detector Development and Performance",
      "value": 0.0067536,
      "subfield": {
        "id": "https://openalex.org/subfields/3106",
        "display_name": "Nuclear and High Energy Physics"
      },
      "field": {
        "id": "https://openalex.org/fields/31",
        "display_name": "Physics and Astronomy"
      },
      "domain": {
        "id": "https://openalex.org/domains/3",
        "display_name": "Physical Sciences"
      }
    },
    {
      "id": "https://openalex.org/T10048",
      "display_name": "Particle physics theoretical and experimental studies",
      "value": 0.0067208,
      "subfield": {
        "id": "https://openalex.org/subfields/3106",
        "display_name": "Nuclear and High Energy Physics"
      },
      "field": {
        "id": "https://openalex.org/fields/31",
        "display_name": "Physics and Astronomy"
      },
      "domain": {
        "id": "https://openalex.org/domains/3",
        "display_name": "Physical Sciences"
      }
    },
    {
      "id": "https://openalex.org/T10347",
      "display_name": "Atmospheric aerosols and clouds",
      "value": 0.0061567,
      "subfield": {
        "id": "https://openalex.org/subfields/2306",
        "display_name": "Global and Planetary Change"
      },
      "field": {
        "id": "https://openalex.org/fields/23",
        "display_name": "Environmental Science"
      },
      "domain": {
        "id": "https://openalex.org/domains/3",
        "display_name": "Physical Sciences"
      }
    },
    {
      "id": "https://openalex.org/T11121",
      "display_name": "Public Relations and Crisis Communication",
      "value": 0.005096,
      "subfield": {
        "id": "https://openalex.org/subfields/3315",
        "display_name": "Communication"
      },
      "field": {
        "id": "https://openalex.org/fields/33",
        "display_name": "Social Sciences"
      },
      "domain": {
        "id": "https://openalex.org/domains/2",
        "display_name": "Social Sciences"
      }
    },
    {
      "id": "https://openalex.org/T13682",
      "display_name": "Engineering Education and Pedagogy",
      "value": 0.0049999,
      "subfield": {
        "id": "https://openalex.org/subfields/2216",
        "display_name": "Architecture"
      },
      "field": {
        "id": "https://openalex.org/fields/22",
        "display_name": "Engineering"
      },
      "domain": {
        "id": "https://openalex.org/domains/3",
        "display_name": "Physical Sciences"
      }
    },
    {
      "id": "https://openalex.org/T11090",
      "display_name": "Dark Matter and Cosmic Phenomena",
      "value": 0.004934,
      "subfield": {
        "id": "https://openalex.org/subfields/3106",
        "display_name": "Nuclear and High Energy Physics"
      },
      "field": {
        "id": "https://openalex.org/fields/31",
        "display_name": "Physics and Astronomy"
      },
      "domain": {
        "id": "https://openalex.org/domains/3",
        "display_name": "Physical Sciences"
      }
    },
    {
      "id": "https://openalex.org/T11323",
      "display_name": "Gamma-ray bursts and supernovae",
      "value": 0.0046766,
      "subfield": {
        "id": "https://openalex.org/subfields/3103",
        "display_name": "Astronomy and Astrophysics"
      },
      "field": {
        "id": "https://openalex.org/fields/31",
        "display_name": "Physics and Astronomy"
      },
      "domain": {
        "id": "https://openalex.org/domains/3",
        "display_name": "Physical Sciences"
      }
    },
    {
      "id": "https://openalex.org/T12593",
      "display_name": "Communication in Education and Healthcare",
      "value": 0.0046539,
      "subfield": {
        "id": "https://openalex.org/subfields/3207",
        "display_name": "Social Psychology"
      },
      "field": {
        "id": "https://openalex.org/fields/32",
        "display_name": "Psychology"
      },
      "domain": {
        "id": "https://openalex.org/domains/2",
        "display_name": "Social Sciences"
      }
    },
    {
      "id": "https://openalex.org/T13050",
      "display_name": "Oil and Gas Production Techniques",
      "value": 0.0046134,
      "subfield": {
        "id": "https://openalex.org/subfields/2212",
        "display_name": "Ocean Engineering"
      },
      "field": {
        "id": "https://openalex.org/fields/22",
        "display_name": "Engineering"
      },
      "domain": {
        "id": "https://openalex.org/domains/3",
        "display_name": "Physical Sciences"
      }
    },
    {
      "id": "https://openalex.org/T10399",
      "display_name": "Hydrocarbon exploration and reservoir analysis",
      "value": 0.0045284,
      "subfield": {
        "id": "https://openalex.org/subfields/2211",
        "display_name": "Mechanics of Materials"
      },
      "field": {
        "id": "https://openalex.org/fields/22",
        "display_name": "Engineering"
      },
      "domain": {
        "id": "https://openalex.org/domains/3",
        "display_name": "Physical Sciences"
      }
    },
    {
      "id": "https://openalex.org/T13121",
      "display_name": "Radio Wave Propagation Studies",
      "value": 0.0044267,
      "subfield": {
        "id": "https://openalex.org/subfields/2202",
        "display_name": "Aerospace Engineering"
      },
      "field": {
        "id": "https://openalex.org/fields/22",
        "display_name": "Engineering"
      },
      "domain": {
        "id": "https://openalex.org/domains/3",
        "display_name": "Physical Sciences"
      }
    },
    {
      "id": "https://openalex.org/T10970",
      "display_name": "Team Dynamics and Performance",
      "value": 0.0043905,
      "subfield": {
        "id": "https://openalex.org/subfields/3207",
        "display_name": "Social Psychology"
      },
      "field": {
        "id": "https://openalex.org/fields/32",
        "display_name": "Psychology"
      },
      "domain": {
        "id": "https://openalex.org/domains/2",
        "display_name": "Social Sciences"
      }
    },
    {
      "id": "https://openalex.org/T10224",
      "display_name": "Quantum Chromodynamics and Particle Interactions",
      "value": 0.0041249,
      "subfield": {
        "id": "https://openalex.org/subfields/3106",
        "display_name": "Nuclear and High Energy Physics"
      },
      "field": {
        "id": "https://openalex.org/fields/31",
        "display_name": "Physics and Astronomy"
      },
      "domain": {
        "id": "https://openalex.org/domains/3",
        "display_name": "Physical Sciences"
      }
    },
    {
      "id": "https://openalex.org/T13025",
      "display_name": "American History and Culture",
      "value": 0.0040907,
      "subfield": {
        "id": "https://openalex.org/subfields/1406",
        "display_name": "Marketing"
      },
      "field": {
        "id": "https://openalex.org/fields/14",
        "display_name": "Business, Management and Accounting"
      },
      "domain": {
        "id": "https://openalex.org/domains/2",
        "display_name": "Social Sciences"
      }
    },
    {
      "id": "https://openalex.org/T11588",
      "display_name": "Atmospheric and Environmental Gas Dynamics",
      "value": 0.0040542,
      "subfield": {
        "id": "https://openalex.org/subfields/2306",
        "display_name": "Global and Planetary Change"
      },
      "field": {
        "id": "https://openalex.org/fields/23",
        "display_name": "Environmental Science"
      },
      "domain": {
        "id": "https://openalex.org/domains/3",
        "display_name": "Physical Sciences"
      }
    }
  ],
  "is_super_system": false,
  "works_api_url": "https://api.openalex.org/works?filter=institutions.id:I8692664",
  "updated_date": "2026-03-03T06:01:00",
  "created_date": "2016-06-24T00:00:00"
}